{
  "generated_at": "2026-03-27 22:21:54",
  "start_date": "2026-03-12",
  "latest_date": "2026-03-27",
  "rows": [
    {
      "date": "2026-03-12",
      "range_label": "2026-03-12 ~ 2026-03-12",
      "samsung": {
        "daily_contracts": -15717,
        "daily_amount": -295.29,
        "cum_contracts": -15717,
        "cum_amount": -295.29,
        "oi": 3970650,
        "oi_delta": 0,
        "spot_shares": -4889647,
        "spot_amount": -9161.56,
        "oi_ratio": -0.3958293982093612
      },
      "skhynix": {
        "daily_contracts": -14835,
        "daily_amount": -1406.17,
        "cum_contracts": -14835,
        "cum_amount": -1406.17,
        "oi": 1015153,
        "oi_delta": 0,
        "spot_shares": -562010,
        "spot_amount": -5260.44,
        "oi_ratio": -1.4613560714493283
      },
      "market": {
        "kospi200_daily_contracts": -6905,
        "kospi200_daily_amount": -14264.02,
        "kospi200_cum_contracts": -6905,
        "kospi200_cum_amount": -14264.02,
        "program_arb_amount": -551.08,
        "program_nonarb_amount": -15149.01
      },
      "notes": "자동 적재. 파일: KRX_투자자별거래실적_주식선물_삼성전자_20260312.xlsx, KRX_투자자별거래실적_주식선물_SK하이닉스_20260312.xlsx, KRX_투자자별거래실적_코스피200선물_20260312.xlsx, KRX_프로그램매매_코스피_20260312.xlsx, KRX_투자자별거래실적_개별종목_삼성전자_20260312.xlsx, KRX_투자자별거래실적_개별종목_SK하이닉스_20260312.xlsx, data_4459_20260312.csv"
    },
    {
      "date": "2026-03-13",
      "range_label": "2026-03-12 ~ 2026-03-13",
      "samsung": {
        "daily_contracts": 57130,
        "daily_amount": 1053.98,
        "cum_contracts": 41413,
        "cum_amount": 758.69,
        "oi": 3993219,
        "oi_delta": 22569,
        "spot_shares": -2847845,
        "spot_amount": -5219.08,
        "oi_ratio": 1.430675352391141
      },
      "skhynix": {
        "daily_contracts": -264,
        "daily_amount": -20.88,
        "cum_contracts": -15099,
        "cum_amount": -1427.0500000000002,
        "oi": 1016881,
        "oi_delta": 1728,
        "spot_shares": -205127,
        "spot_amount": -1841.85,
        "oi_ratio": -0.025961739869266906
      },
      "market": {
        "kospi200_daily_contracts": -321,
        "kospi200_daily_amount": -556.39,
        "kospi200_cum_contracts": -7226,
        "kospi200_cum_amount": -14820.41,
        "program_arb_amount": -2458.56,
        "program_nonarb_amount": -13183.89
      },
      "notes": "자동 적재. 파일: KRX_투자자별거래실적_주식선물_삼성전자_20260313.xlsx, KRX_투자자별거래실적_주식선물_SK하이닉스_20260313.xlsx, KRX_투자자별거래실적_코스피200선물_20260313.xlsx, KRX_프로그램매매_코스피_20260313.xlsx, KRX_투자자별거래실적_개별종목_삼성전자_20260313.xlsx, KRX_투자자별거래실적_개별종목_SK하이닉스_20260313.xlsx, data_4459_20260313.csv"
    },
    {
      "date": "2026-03-16",
      "range_label": "2026-03-12 ~ 2026-03-16",
      "samsung": {
        "daily_contracts": 90311,
        "daily_amount": 1687.22,
        "cum_contracts": 131724,
        "cum_amount": 2445.91,
        "oi": 4244644,
        "oi_delta": 251425,
        "spot_shares": -498635,
        "spot_amount": -916.56,
        "oi_ratio": 2.127646040516001
      },
      "skhynix": {
        "daily_contracts": 25525,
        "daily_amount": 2473.11,
        "cum_contracts": 10426,
        "cum_amount": 1046.06,
        "oi": 1081841,
        "oi_delta": 64960,
        "spot_shares": 324950,
        "spot_amount": 3075.78,
        "oi_ratio": 2.3594040159321006
      },
      "market": {
        "kospi200_daily_contracts": -3280,
        "kospi200_daily_amount": -6680.16,
        "kospi200_cum_contracts": -10506,
        "kospi200_cum_amount": -21500.57,
        "program_arb_amount": -953.47,
        "program_nonarb_amount": -7526.69
      },
      "notes": "자동 적재. 파일: KRX_투자자별거래실적_주식선물_삼성전자_20260316.xlsx, KRX_투자자별거래실적_주식선물_SK하이닉스_20260316.xlsx, KRX_투자자별거래실적_코스피200선물_20260316.xlsx, KRX_프로그램매매_코스피_20260316.xlsx, KRX_투자자별거래실적_개별종목_삼성전자_20260316.xlsx, KRX_투자자별거래실적_개별종목_SK하이닉스_20260316.xlsx, data_4459_20260316.csv"
    },
    {
      "date": "2026-03-17",
      "range_label": "2026-03-12 ~ 2026-03-17",
      "samsung": {
        "daily_contracts": 4134,
        "daily_amount": 164.58,
        "cum_contracts": 135858,
        "cum_amount": 2610.49,
        "oi": 4366108,
        "oi_delta": 121464,
        "spot_shares": 386050,
        "spot_amount": 757.59,
        "oi_ratio": 0.09468386947826302
      },
      "skhynix": {
        "daily_contracts": -8101,
        "daily_amount": -801.26,
        "cum_contracts": 2325,
        "cum_amount": 244.79999999999995,
        "oi": 1084878,
        "oi_delta": 3037,
        "spot_shares": -220808,
        "spot_amount": -2179.49,
        "oi_ratio": -0.7467199076762548
      },
      "market": {
        "kospi200_daily_contracts": -87,
        "kospi200_daily_amount": -124.93,
        "kospi200_cum_contracts": -10593,
        "kospi200_cum_amount": -21625.5,
        "program_arb_amount": 718.65,
        "program_nonarb_amount": -6300.99
      },
      "notes": "자동 적재. 파일: KRX_투자자별거래실적_주식선물_삼성전자_20260317.xlsx, KRX_투자자별거래실적_주식선물_SK하이닉스_20260317.xlsx, KRX_투자자별거래실적_코스피200선물_20260317.xlsx, KRX_프로그램매매_코스피_20260317.xlsx, KRX_투자자별거래실적_개별종목_삼성전자_20260317.xlsx, KRX_투자자별거래실적_개별종목_SK하이닉스_20260317.xlsx, data_4459_20260317.csv"
    },
    {
      "date": "2026-03-18",
      "range_label": "2026-03-12 ~ 2026-03-18",
      "samsung": {
        "daily_contracts": -3900,
        "daily_amount": -71.11,
        "cum_contracts": 131958,
        "cum_amount": 2539.3799999999997,
        "oi": 4571077,
        "oi_delta": 204969,
        "spot_shares": 1375923,
        "spot_amount": 2815.6,
        "oi_ratio": -0.0853190615690788
      },
      "skhynix": {
        "daily_contracts": 31960,
        "daily_amount": 3331.66,
        "cum_contracts": 34285,
        "cum_amount": 3576.46,
        "oi": 1098489,
        "oi_delta": 13611,
        "spot_shares": 582363,
        "spot_amount": 5933.32,
        "oi_ratio": 2.9094510732469785
      },
      "market": {
        "kospi200_daily_contracts": 7850,
        "kospi200_daily_amount": 17002.01,
        "kospi200_cum_contracts": -2743,
        "kospi200_cum_amount": -4623.490000000002,
        "program_arb_amount": 8667.8,
        "program_nonarb_amount": 7800.86
      },
      "notes": "자동 적재. 파일: KRX_투자자별거래실적_주식선물_삼성전자_20260318.xlsx, KRX_투자자별거래실적_주식선물_SK하이닉스_20260318.xlsx, KRX_투자자별거래실적_코스피200선물_20260318.xlsx, KRX_프로그램매매_코스피_20260318.xlsx, KRX_투자자별거래실적_개별종목_삼성전자_20260318.xlsx, KRX_투자자별거래실적_개별종목_SK하이닉스_20260318.xlsx, data_4459_20260318.csv"
    },
    {
      "date": "2026-03-19",
      "range_label": "2026-03-12 ~ 2026-03-19",
      "samsung": {
        "daily_contracts": -105328,
        "daily_amount": -2122.97,
        "cum_contracts": 26630,
        "cum_amount": 416.40999999999985,
        "oi": 4721746,
        "oi_delta": 150669,
        "spot_shares": -2145636,
        "spot_amount": -4301.73,
        "oi_ratio": -2.2307002536773473
      },
      "skhynix": {
        "daily_contracts": -19143,
        "daily_amount": -1938.56,
        "cum_contracts": 15142,
        "cum_amount": 1637.9,
        "oi": 1064859,
        "oi_delta": -33630,
        "spot_shares": -461105,
        "spot_amount": -4677.78,
        "oi_ratio": -1.7977027944544772
      },
      "market": {
        "kospi200_daily_contracts": -7759,
        "kospi200_daily_amount": -16807.19,
        "kospi200_cum_contracts": -10502,
        "kospi200_cum_amount": -21430.68,
        "program_arb_amount": -796.22,
        "program_nonarb_amount": -19786.51
      },
      "notes": "자동 적재. 파일: KRX_투자자별거래실적_주식선물_삼성전자_20260319.xlsx, KRX_투자자별거래실적_주식선물_SK하이닉스_20260319.xlsx, KRX_투자자별거래실적_코스피200선물_20260319.xlsx, KRX_프로그램매매_코스피_20260319.xlsx, KRX_투자자별거래실적_개별종목_삼성전자_20260319.xlsx, KRX_투자자별거래실적_개별종목_SK하이닉스_20260319.xlsx, data_4459_20260319.csv"
    },
    {
      "date": "2026-03-20",
      "range_label": "2026-03-12 ~ 2026-03-20",
      "samsung": {
        "daily_contracts": -98493,
        "daily_amount": -1970.02,
        "cum_contracts": -71863,
        "cum_amount": -1553.6100000000001,
        "oi": 4769362,
        "oi_delta": 47616,
        "spot_shares": -217834,
        "spot_amount": -823.44,
        "oi_ratio": -2.065118982371227
      },
      "skhynix": {
        "daily_contracts": 5610,
        "daily_amount": 581.36,
        "cum_contracts": 20752,
        "cum_amount": 2219.26,
        "oi": 1073591,
        "oi_delta": 8732,
        "spot_shares": -719644,
        "spot_amount": -7284.96,
        "oi_ratio": 0.522545364109796
      },
      "market": {
        "kospi200_daily_contracts": -1521,
        "kospi200_daily_amount": -3286.25,
        "kospi200_cum_contracts": -12023,
        "kospi200_cum_amount": -24716.93,
        "program_arb_amount": 447.22,
        "program_nonarb_amount": -17849.53
      },
      "notes": "자동 적재. 파일: KRX_투자자별거래실적_주식선물_삼성전자_20260320.xlsx, KRX_투자자별거래실적_주식선물_SK하이닉스_20260320.xlsx, KRX_투자자별거래실적_코스피200선물_20260320.xlsx, KRX_프로그램매매_코스피_20260320.xlsx, KRX_투자자별거래실적_개별종목_삼성전자_20260320.xlsx, KRX_투자자별거래실적_개별종목_SK하이닉스_20260320.xlsx, data_4459_20260320.csv"
    },
    {
      "date": "2026-03-23",
      "range_label": "2026-03-12 ~ 2026-03-23",
      "samsung": {
        "daily_contracts": -48771,
        "daily_amount": -917.74,
        "cum_contracts": -120634,
        "cum_amount": -2471.3500000000004,
        "oi": 4773183,
        "oi_delta": 3821,
        "spot_shares": -8062631,
        "spot_amount": -15203.27,
        "oi_ratio": -1.0217710068941417
      },
      "skhynix": {
        "daily_contracts": -43781,
        "daily_amount": -4079.99,
        "cum_contracts": -23029,
        "cum_amount": -1860.7299999999996,
        "oi": 989946,
        "oi_delta": -83645,
        "spot_shares": -185688,
        "spot_amount": -1772.12,
        "oi_ratio": -4.4225644631121295
      },
      "market": {
        "kospi200_daily_contracts": -10826,
        "kospi200_daily_amount": -22391.82,
        "kospi200_cum_contracts": -22849,
        "kospi200_cum_amount": -47108.75,
        "program_arb_amount": -7159.52,
        "program_nonarb_amount": -29756.69
      },
      "notes": "자동 적재. 파일: KRX_투자자별거래실적_주식선물_삼성전자_20260323.xlsx, KRX_투자자별거래실적_주식선물_SK하이닉스_20260323.xlsx, KRX_투자자별거래실적_코스피200선물_20260323.xlsx, KRX_프로그램매매_코스피_20260323.xlsx, KRX_투자자별거래실적_개별종목_삼성전자_20260323.xlsx, KRX_투자자별거래실적_개별종목_SK하이닉스_20260323.xlsx, data_4459_20260323.csv"
    },
    {
      "date": "2026-03-24",
      "range_label": "2026-03-12 ~ 2026-03-24",
      "samsung": {
        "daily_contracts": 185577,
        "daily_amount": 3479.07,
        "cum_contracts": 64943,
        "cum_amount": 1007.7199999999998,
        "oi": 4591767,
        "oi_delta": -181416,
        "spot_shares": -6154379,
        "spot_amount": -11672.46,
        "oi_ratio": 4.041516043823652
      },
      "skhynix": {
        "daily_contracts": 10833,
        "daily_amount": 1058.85,
        "cum_contracts": -12196,
        "cum_amount": -801.8799999999997,
        "oi": 1036381,
        "oi_delta": 46435,
        "spot_shares": -290396,
        "spot_amount": -2843.09,
        "oi_ratio": 1.045271960794341
      },
      "market": {
        "kospi200_daily_contracts": 1857,
        "kospi200_daily_amount": 3836.9,
        "kospi200_cum_contracts": -20992,
        "kospi200_cum_amount": -43271.85,
        "program_arb_amount": 3061.27,
        "program_nonarb_amount": -17906.75
      },
      "notes": "자동 적재. 파일: KRX_투자자별거래실적_주식선물_삼성전자_20260324.xlsx, KRX_투자자별거래실적_주식선물_SK하이닉스_20260324.xlsx, KRX_투자자별거래실적_코스피200선물_20260324.xlsx, KRX_프로그램매매_코스피_20260324.xlsx, KRX_투자자별거래실적_개별종목_삼성전자_20260324.xlsx, KRX_투자자별거래실적_개별종목_SK하이닉스_20260324.xlsx, data_4459_20260324.csv"
    },
    {
      "date": "2026-03-25",
      "range_label": "2026-03-12 ~ 2026-03-25",
      "samsung": {
        "daily_contracts": -34424,
        "daily_amount": -671.47,
        "cum_contracts": 30519,
        "cum_amount": 336.2499999999998,
        "oi": 4553222,
        "oi_delta": -38545,
        "spot_shares": -6169278,
        "spot_amount": -11800.99,
        "oi_ratio": -0.7560360553471805
      },
      "skhynix": {
        "daily_contracts": 31936,
        "daily_amount": 3240.15,
        "cum_contracts": 19740,
        "cum_amount": 2438.2700000000004,
        "oi": 1066832,
        "oi_delta": 30451,
        "spot_shares": -396640,
        "spot_amount": -3901.84,
        "oi_ratio": 2.9935360019197024
      },
      "market": {
        "kospi200_daily_contracts": 7551,
        "kospi200_daily_amount": 16080.99,
        "kospi200_cum_contracts": -13441,
        "kospi200_cum_amount": -27190.86,
        "program_arb_amount": 4554.59,
        "program_nonarb_amount": -7056.7
      },
      "notes": "자동 적재. 파일: KRX_투자자별거래실적_주식선물_삼성전자_20260325.xlsx, KRX_투자자별거래실적_주식선물_SK하이닉스_20260325.xlsx, KRX_투자자별거래실적_코스피200선물_20260325.xlsx, KRX_프로그램매매_코스피_20260325.xlsx, KRX_투자자별거래실적_개별종목_삼성전자_20260325.xlsx, KRX_투자자별거래실적_개별종목_SK하이닉스_20260325.xlsx, data_4459_20260325.csv"
    },
    {
      "date": "2026-03-26",
      "range_label": "2026-03-12 ~ 2026-03-26",
      "samsung": {
        "daily_contracts": -6978,
        "daily_amount": -129.57,
        "cum_contracts": 23541,
        "cum_amount": 206.67999999999978,
        "oi": 4448967,
        "oi_delta": -104255,
        "spot_shares": -11190838,
        "spot_amount": -20408.11,
        "oi_ratio": -0.1568453980440853
      },
      "skhynix": {
        "daily_contracts": 266,
        "daily_amount": 45.51,
        "cum_contracts": 20006,
        "cum_amount": 2483.7800000000007,
        "oi": 995639,
        "oi_delta": -71193,
        "spot_shares": -835124,
        "spot_amount": -7906.73,
        "oi_ratio": 0.026716510703176554
      },
      "market": {
        "kospi200_daily_contracts": 1595,
        "kospi200_daily_amount": 3206.68,
        "kospi200_cum_contracts": -11846,
        "kospi200_cum_amount": -23984.18,
        "program_arb_amount": 2338.74,
        "program_nonarb_amount": -18599.37
      },
      "notes": "자동 적재. 파일: KRX_투자자별거래실적_주식선물_삼성전자_20260326.xlsx, KRX_투자자별거래실적_주식선물_SK하이닉스_20260326.xlsx, KRX_투자자별거래실적_코스피200선물_20260326.xlsx, KRX_프로그램매매_코스피_20260326.xlsx, KRX_투자자별거래실적_개별종목_삼성전자_20260326.xlsx, KRX_투자자별거래실적_개별종목_SK하이닉스_20260326.xlsx, data_4459_20260326.csv"
    },
    {
      "date": "2026-03-27",
      "range_label": "2026-03-12 ~ 2026-03-27",
      "samsung": {
        "daily_contracts": -55131,
        "daily_amount": -974.77,
        "cum_contracts": -31590,
        "cum_amount": -768.0900000000001,
        "oi": 4456195,
        "oi_delta": 7228,
        "spot_shares": -10266640,
        "spot_amount": -17985.69,
        "oi_ratio": -1.237176559822898
      },
      "skhynix": {
        "daily_contracts": 4339,
        "daily_amount": 376.08,
        "cum_contracts": 24345,
        "cum_amount": 2859.8600000000006,
        "oi": 1033772,
        "oi_delta": 38133,
        "spot_shares": -1269995,
        "spot_amount": -11464.25,
        "oi_ratio": 0.4197250457547699
      },
      "market": {
        "kospi200_daily_contracts": -2262,
        "kospi200_daily_amount": -4388.31,
        "kospi200_cum_contracts": -14108,
        "kospi200_cum_amount": -28372.49,
        "program_arb_amount": 229.96,
        "program_nonarb_amount": -19391.37
      },
      "notes": "자동 적재. 파일: KRX_투자자별거래실적_주식선물_삼성전자_20260327.xlsx, KRX_투자자별거래실적_주식선물_SK하이닉스_20260327.xlsx, KRX_투자자별거래실적_코스피200선물_20260327.xlsx, KRX_프로그램매매_코스피_20260327.xlsx, KRX_투자자별거래실적_개별종목_삼성전자_20260327.xlsx, KRX_투자자별거래실적_개별종목_SK하이닉스_20260327.xlsx, data_4459_20260327.csv"
    }
  ]
}